MANIFEST.in
setup.py
synthesis
synthesis.egg-info
synthesis/README.txt
synthesis/README_VersionControlDB.txt
synthesis/__init__.py
synthesis/__init__.pyc
synthesis/borg.py
synthesis/borg.pyc
synthesis/build.sh
synthesis/clsexceptions.py
synthesis/clsexceptions.pyc
synthesis/clsiniutils.py
synthesis/clspostprocessing.py
synthesis/clssecurity.py
synthesis/clssecurity.pyc
synthesis/clssocketcomm.py
synthesis/clssocketcomm.pyc
synthesis/conf
synthesis/config
synthesis/controllers
synthesis/dateutils.py
synthesis/dbobjects.py
synthesis/dbobjects.pyc
synthesis/dbobjects_unit_test.py
synthesis/emailprocessor.py
synthesis/emailprocessor.pyc
synthesis/errcatalog
synthesis/failed_files
synthesis/fileinput_unit_test_file_exists.py
synthesis/fileinput_unit_test_no_file.py
synthesis/fileinputwatcher.py
synthesis/fileinputwatcher.pyc
synthesis/filerouter.py
synthesis/filerouter.pyc
synthesis/fileutils.py
synthesis/fileutils.pyc
synthesis/hmiscsv27writer.py
synthesis/hmiscsv30reader.py
synthesis/hmiscsv30writer.py
synthesis/hmisxml28reader.py
synthesis/hmisxml28reader.pyc
synthesis/hmisxml28writer.py
synthesis/hmisxml30reader.py
synthesis/hmisxml30reader.pyc
synthesis/hmisxml30writer.py
synthesis/httpheader.log
synthesis/iniutils.py
synthesis/input_files
synthesis/interpretpicklist.py
synthesis/jfcsxmlreader.py
synthesis/jfcsxmlreader.pyc
synthesis/lib
synthesis/loadconfiguration.py
synthesis/logger.py
synthesis/logger.pyc
synthesis/logging.ini
synthesis/logs
synthesis/lxmlvalidationtest.py
synthesis/main.py
synthesis/mainframe.py
synthesis/mainprocessor.py
synthesis/mainprocessor.pyc
synthesis/manage.py
synthesis/model
synthesis/nodebuilder.py
synthesis/occhmisxml30reader.py
synthesis/occhmisxml30reader.pyc
synthesis/output_files
synthesis/parhmisxml30reader.py
synthesis/parxmlreader.py
synthesis/postgresutils.py
synthesis/postgresutils.pyc
synthesis/public
synthesis/queryobject.py
synthesis/reader.py
synthesis/reader.pyc
synthesis/security_unit_test.py
synthesis/selector.py
synthesis.egg-info/PKG-INFO
synthesis.egg-info/SOURCES.txt
synthesis.egg-info/dependency_links.txt
synthesis.egg-info/requires.txt
synthesis.egg-info/top_level.txt
synthesis/synthesis.egg-info/PKG-INFO
synthesis/synthesis.egg-info/SOURCES.txt
synthesis/synthesis.egg-info/dependency_links.txt
synthesis/synthesis.egg-info/index.html
synthesis/synthesis.egg-info/top_level.txt
