Metadata-Version: 1.0
Name: synthesis
Version: 1.1061
Summary: Health and Human Services Data Integration Server
Home-page: http://xsd.alexandriaconsulting.com/repos/trunk/synthesis/src
Author: Alexandria Consulting LLC
Author-email: eric@alexandriaconsulting.com
License: MIT
Keywords: human services data integration hmis 211 niem
Platform: Linux
Classifier: Programming Language :: Python
